tkextras/__init__.py
tkextras/treeview_dataframe.py
tkextras/widgets_render.py
tkextras-1.1.0.dist-info/LICENSE
tkextras-1.1.0.dist-info/METADATA
tkextras-1.1.0.dist-info/WHEEL
tkextras-1.1.0.dist-info/top_level.txt
tkextras-1.1.0.dist-info/RECORD
