Metadata-Version: 2.2
Name: tkextras
Version: 1.1.0
Summary: A Tkinter utility module for enhanced widgets rendering
Home-page: https://github.com/whellcome/tkextras
Download-URL: https://github.com/whellcome/tkextras/archive/master.zip
Author: Dietmar Steinle
License: MIT
Project-URL: Documentation, https://tkextras.readthedocs.io/
Project-URL: Source Code, https://github.com/whellcome/tkextras/tree/master/tkextras
Project-URL: Examples, https://github.com/whellcome/tkextras/tree/master/examples
Keywords: tkinter,ttk,gui
Classifier: Programming Language :: Python :: 3
Classifier: License :: OSI Approved :: MIT License
Classifier: Operating System :: OS Independent
Classifier: Topic :: Software Development :: Libraries :: Tcl Extensions
Classifier: Topic :: Software Development :: Libraries :: Python Modules
Requires-Python: >=3.9
License-File: LICENSE
Requires-Dist: pandas>=1.0
Dynamic: author
Dynamic: classifier
Dynamic: description
Dynamic: description-content-type
Dynamic: download-url
Dynamic: home-page
Dynamic: keywords
Dynamic: license
Dynamic: project-url
Dynamic: requires-dist
Dynamic: requires-python
Dynamic: summary
